roche/crisp/__init__.py
roche/crisp/__version__.py
roche/crisp/main.py
roche/crisp/py.typed
roche/crisp/callbacks/__init__.py
roche/crisp/callbacks/data_visualizer.py
roche/crisp/datamodules/__init__.py
roche/crisp/datamodules/base_datamodule.py
roche/crisp/datamodules/base_dataset.py
roche/crisp/datamodules/cellpose_dataset.py
roche/crisp/datamodules/custom_datamodules.py
roche/crisp/datamodules/input_data/__init__.py
roche/crisp/datamodules/input_data/input_data.py
roche/crisp/inference/__init__.py
roche/crisp/inference/cellpose_inference.py
roche/crisp/inference/cellpose_inference_unoptimized.py
roche/crisp/inference/mtl_inference.py
roche/crisp/inference/nuclei_detection_base.py
roche/crisp/inference/nuclei_detection_cellpose.py
roche/crisp/inference/nuclei_detection_mtl.py
roche/crisp/inference/nuclei_detection_studio.py
roche/crisp/inference/nuclei_information.py
roche/crisp/losses/__init__.py
roche/crisp/losses/instanseg_loss.py
roche/crisp/metrics/__init__.py
roche/crisp/metrics/_metric_computations.py
roche/crisp/metrics/concordance_corr_coef.py
roche/crisp/metrics/detection_stats.py
roche/crisp/metrics/instanseg_metric.py
roche/crisp/metrics/region_segmentation_stats.py
roche/crisp/metrics/segmentation_stats.py
roche/crisp/model_engines/__init__.py
roche/crisp/model_engines/base_model_engine.py
roche/crisp/model_engines/cell_detection_engine.py
roche/crisp/model_engines/cell_segmentation_engine.py
roche/crisp/model_engines/instanseg_engine.py
roche/crisp/model_engines/region_segmentation_engine.py
roche/crisp/networks/__init__.py
roche/crisp/networks/cellpose.py
roche/crisp/networks/instanseg_unet.py
roche/crisp/networks/mtl_residual_unet.py
roche/crisp/networks/unet.py
roche/crisp/networks/vitunet.py
roche/crisp/utils/__init__.py
roche/crisp/utils/cellpose_metrics.py
roche/crisp/utils/cellpose_utils.py
roche/crisp/utils/common_utils.py
roche/crisp/utils/create_gallery.py
roche/crisp/utils/detection_utils.py
roche/crisp/utils/generate_gaussian_masks.py
roche_crisp-0.0.2.dist-info/METADATA
roche_crisp-0.0.2.dist-info/WHEEL
roche_crisp-0.0.2.dist-info/entry_points.txt
roche_crisp-0.0.2.dist-info/top_level.txt
roche_crisp-0.0.2.dist-info/RECORD
