Metadata-Version: 2.4
Name: roche.crisp
Version: 0.0.2
Summary: Framework for Cell & Region Image Segmentation/Classification
Author-email: Nazim Shaikh <nazim.shaikh@roche.com>, Kamil Wasag <kamil.wasag.kw1@roche.com>, Srinath Jayachandran <srinath.jayachandran@roche.com>, Ruben Bagan Benavides <ruben.bagan_benavides@roche.com>
Maintainer-email: Nazim Shaikh <nazim.shaikh@roche.com>, Srinath Jayachandran <srinath.jayachandran@roche.com>
Project-URL: homepage, https://code.roche.com/rds-csi-dp/crisp-ai
Requires-Python: >=3.11
Requires-Dist: wandb
Requires-Dist: fastremap
Requires-Dist: csbdeep
Requires-Dist: einops
Requires-Dist: edt
Requires-Dist: matplotlib
Requires-Dist: joblib
Requires-Dist: tqdm
Requires-Dist: hydra-core
Requires-Dist: onnx
Requires-Dist: onnxruntime
Requires-Dist: onnxruntime-gpu
Requires-Dist: stardist
Requires-Dist: monai
Requires-Dist: streamlit
Requires-Dist: loguru
Requires-Dist: lightning==2.5.1
Requires-Dist: scikit-learn==1.4.0
Requires-Dist: torch==2.5.1
Requires-Dist: timm==1.0.15
Requires-Dist: torchvision==0.20.1
Requires-Dist: imageio==2.37.0
Requires-Dist: numba==0.61.2
Requires-Dist: scikit-image==0.25.2
Requires-Dist: albumentations==2.0.8
Requires-Dist: opencv-contrib-python-headless==4.11.0.86
Requires-Dist: scipy==1.15.3
Requires-Dist: pandas==2.2.0
Requires-Dist: numpy==1.26.4
Requires-Dist: typer>=0.16.0
Requires-Dist: typeguard>=4.4.4
Requires-Dist: nvtx>=0.2.13
Provides-Extra: dev
Requires-Dist: ruff; extra == "dev"
Requires-Dist: pydocstringformatter; extra == "dev"
Requires-Dist: pre-commit; extra == "dev"
Provides-Extra: test
Requires-Dist: flake8; extra == "test"
Requires-Dist: flake8-docstrings; extra == "test"
Requires-Dist: mypy; extra == "test"
Requires-Dist: pydocstyle; extra == "test"
Requires-Dist: pyfakefs; extra == "test"
Requires-Dist: pytest; extra == "test"
Requires-Dist: pytest-cov; extra == "test"
Provides-Extra: doc
Requires-Dist: myst-parser; extra == "doc"
Requires-Dist: sphinx; extra == "doc"
Requires-Dist: sphinx-autodoc-typehints; extra == "doc"
Requires-Dist: sphinxcontrib-autoprogram; extra == "doc"
Requires-Dist: sphinx-pyreverse; extra == "doc"
Requires-Dist: sphinx-rtd-theme; extra == "doc"
Provides-Extra: build
Requires-Dist: build; extra == "build"
Requires-Dist: twine; extra == "build"
